{
  "dataset": "spherical_mnist",
  "model": "bispectrum",
  "base_model": "bispectrum",
  "train_mode": "R",
  "test_rotation_seed": 777,
  "seed": 789,
  "lmax": 15,
  "n_params": 231818,
  "invariant_dim": 768,
  "train_size": null,
  "train_examples": 50000,
  "best_val_accuracy": 0.9556,
  "test_c": {
    "loss": 0.16120577639341355,
    "accuracy": 0.9469
  },
  "test": {
    "loss": 0.16120577639341355,
    "accuracy": 0.9469
  },
  "test_nr": {
    "loss": 0.16120577639341355,
    "accuracy": 0.9469
  },
  "test_r": {
    "loss": 0.15971069877147676,
    "accuracy": 0.9477
  },
  "rotation_robustness": {
    "rot_00": 0.9478,
    "rot_01": 0.9477,
    "rot_02": 0.9477,
    "rot_03": 0.9477,
    "rot_04": 0.9475,
    "rot_05": 0.9476,
    "rot_06": 0.9476,
    "rot_07": 0.9476,
    "rot_08": 0.9476,
    "rot_09": 0.9475,
    "mean_accuracy": 0.94763,
    "std_accuracy": 8.999999999999009e-05
  },
  "wall_time_s": 39.5629460811615,
  "epochs_run": 19,
  "peak_train_alloc_bytes": 421850624,
  "peak_train_reserved_bytes": 847249408,
  "gpu_name": "NVIDIA A100-SXM4-80GB",
  "cuda_total_memory_bytes": 85095874560,
  "git_sha": "5fb3903a1c11765c007a1686e1c9acd77b6024db",
  "argv": [
    "--model",
    "bispectrum",
    "--run_label",
    "bispectrum",
    "--train_mode",
    "R",
    "--seed",
    "789",
    "--hidden",
    "256",
    "--lmax",
    "15",
    "--batch_size",
    "256",
    "--output_dir",
    "/home/johmathe/bispectrum/paper/experiments/normalized_results/spherical_mnist/n_full",
    "--data_dir",
    "./smnist_data",
    "--subset_dir",
    "/home/johmathe/bispectrum/paper/experiments/normalized_results/subsets",
    "--test_rotation_seed",
    "777",
    "--patience",
    "10",
    "--epochs",
    "50"
  ]
}